octocruncher/__init__.py
octocruncher/helper_classes.py
octocruncher/octocruncher.py
octocruncher-0.2.0.dist-info/LICENSE
octocruncher-0.2.0.dist-info/METADATA
octocruncher-0.2.0.dist-info/WHEEL
octocruncher-0.2.0.dist-info/top_level.txt
octocruncher-0.2.0.dist-info/RECORD
