Metadata-Version: 2.1
Name: octocruncher
Version: 0.2.0
Summary: A simple package to implement the Octopart API version 4
Home-page: https://github.com/tgross35/octocruncher-v4
Author: Trevor Gross
Author-email: tgross@intrepidcs.com
License: UNKNOWN
Platform: UNKNOWN
Classifier: Programming Language :: Python :: 3
Classifier: License :: OSI Approved :: MIT License
Classifier: Operating System :: OS Independent
Requires-Python: >=3.6
License-File: LICENSE
